kulo/__init__.py
kulo/__main__.py
kulo/api.py
kulo/cli.py
kulo/version.py
kulo-0.0.1.dist-info/LICENSE.txt
kulo-0.0.1.dist-info/METADATA
kulo-0.0.1.dist-info/WHEEL
kulo-0.0.1.dist-info/entry_points.txt
kulo-0.0.1.dist-info/top_level.txt
kulo-0.0.1.dist-info/RECORD
