Metadata-Version: 2.1
Name: kulo
Version: 0.0.1
Summary: A tool for managing (Kumo Cloud-managed) Mitsubishi Heat Pump systems (mostly?) locally
Home-page: https://github.com/duckinator/kulo
Author: Ellen Marie Dash
Author-email: me@duckie.co
License: MIT
Classifier: Programming Language :: Python :: 3
Classifier: Programming Language :: Python :: 3.8
Classifier: Programming Language :: Python :: 3.9
Classifier: Programming Language :: Python :: 3.10
Classifier: Programming Language :: Python :: 3.11
Classifier: License :: OSI Approved :: MIT License
Classifier: Operating System :: OS Independent
Requires-Python: >=3.8
License-File: LICENSE.txt
Requires-Dist: pykumo (==0.3.5)
Requires-Dist: toml (==0.10.2)
Requires-Dist: requests
Provides-Extra: testing
Requires-Dist: pylint (==2.15.9) ; extra == 'testing'
Requires-Dist: pytest (==7.2.0) ; extra == 'testing'
Requires-Dist: pytest-pylint (==0.19.0) ; extra == 'testing'
Requires-Dist: pytest-mypy (==0.10.3) ; extra == 'testing'
Provides-Extra: testing_only
Requires-Dist: pytest (==7.2.0) ; extra == 'testing_only'
